{
  "run": {
    "command": "nx build test-lib-test-lib",
    "startTime": "2025-08-05T09:20:14.913Z",
    "endTime": "2025-08-05T09:20:16.831Z",
    "inner": false
  },
  "tasks": [
    {
      "taskId": "test-lib-test-lib:build",
      "target": "build",
      "projectName": "test-lib-test-lib",
      "hash": "89005025080474359",
      "startTime": "2025-08-05T09:20:14.934Z",
      "endTime": "2025-08-05T09:20:16.639Z",
      "params": "",
      "cacheStatus": "local-cache-hit",
      "status": 0
    }
  ]
}